aiotx/__init__.py
aiotx/exceptions.py
aiotx/log.py
aiotx/clients/__init__.py
aiotx/clients/_base_client.py
aiotx/clients/_evm_base_client.py
aiotx/clients/_ton_base_client.py
aiotx/clients/_tron_base_client.py
aiotx/clients/_utxo_base_client.py
aiotx/types/__init__.py
aiotx/utils/__init__.py
aiotx/utils/bep20_abi.json
aiotx/utils/erc20_abi.json
aiotx/utils/trc20_abi.json
aiotx/utils/utxo_db_models.py
aiotx/utils/tonsdk/__init__.py
aiotx/utils/tonsdk/_exceptions.py
aiotx/utils/tonsdk/boc/__init__.py
aiotx/utils/tonsdk/boc/_bit_string.py
aiotx/utils/tonsdk/boc/_builder.py
aiotx/utils/tonsdk/boc/_cell.py
aiotx/utils/tonsdk/boc/_dict_builder.py
aiotx/utils/tonsdk/boc/dict/__init__.py
aiotx/utils/tonsdk/boc/dict/find_common_prefix.py
aiotx/utils/tonsdk/boc/dict/serialize_dict.py
aiotx/utils/tonsdk/contract/__init__.py
aiotx/utils/tonsdk/contract/token/__init__.py
aiotx/utils/tonsdk/contract/token/ft/__init__.py
aiotx/utils/tonsdk/contract/token/ft/jetton_minter.py
aiotx/utils/tonsdk/contract/token/ft/jetton_wallet.py
aiotx/utils/tonsdk/contract/token/nft/__init__.py
aiotx/utils/tonsdk/contract/token/nft/nft_collection.py
aiotx/utils/tonsdk/contract/token/nft/nft_item.py
aiotx/utils/tonsdk/contract/token/nft/nft_sale.py
aiotx/utils/tonsdk/contract/token/nft/nft_utils.py
aiotx/utils/tonsdk/contract/wallet/__init__.py
aiotx/utils/tonsdk/contract/wallet/_highload_wallet_contract.py
aiotx/utils/tonsdk/contract/wallet/_multisig_wallet_contract.py
aiotx/utils/tonsdk/contract/wallet/_wallet_contract.py
aiotx/utils/tonsdk/contract/wallet/_wallet_contract_v2.py
aiotx/utils/tonsdk/contract/wallet/_wallet_contract_v3.py
aiotx/utils/tonsdk/contract/wallet/_wallet_contract_v4.py
aiotx/utils/tonsdk/crypto/__init__.py
aiotx/utils/tonsdk/crypto/_keystore.py
aiotx/utils/tonsdk/crypto/_mnemonic.py
aiotx/utils/tonsdk/crypto/_settings.py
aiotx/utils/tonsdk/crypto/_utils.py
aiotx/utils/tonsdk/crypto/exceptions.py
aiotx/utils/tonsdk/crypto/bip39/__init__.py
aiotx-10.0.0.dist-info/licenses/LICENSE
aiotx-10.0.0.dist-info/METADATA
aiotx-10.0.0.dist-info/WHEEL
aiotx-10.0.0.dist-info/top_level.txt
aiotx-10.0.0.dist-info/RECORD
