Metadata-Version: 2.4
Name: aiotx
Version: 10.0.0
Summary: An asynchronous library for interacting with various cryptocurrencies and blockchains
Home-page: https://github.com/Grommash9/aiotx
Author: Oleksandr Prudnikov
Author-email: prudnikov21@icloud.com
Project-URL: Documentation, https://grommash9.github.io/aiotx/
Project-URL: Source, https://github.com/Grommash9/aiotx
Keywords: cryptocurrency,blockchain,bitcoin,ethereum,asyncio,aiohttp,json-rpc,payment,wallet,transaction
Classifier: Development Status :: 3 - Alpha
Classifier: Intended Audience :: Developers
Classifier: License :: OSI Approved :: MIT License
Classifier: Programming Language :: Python :: 3.10
Classifier: Programming Language :: Python :: 3.11
Classifier: Programming Language :: Python :: 3.12
License-File: LICENSE
Requires-Dist: aiohttp
Requires-Dist: setuptools
Requires-Dist: pynacl>=1.4.0
Requires-Dist: tronpy
Provides-Extra: test
Requires-Dist: hypothesis; extra == "test"
Requires-Dist: ruff; extra == "test"
Requires-Dist: pyproj; extra == "test"
Requires-Dist: pytest; extra == "test"
Requires-Dist: pytest-cov; extra == "test"
Requires-Dist: sphinx; extra == "test"
Requires-Dist: pytest-asyncio; extra == "test"
Requires-Dist: tox; extra == "test"
Requires-Dist: build; extra == "test"
Requires-Dist: vcrpy; extra == "test"
Provides-Extra: utxo
Requires-Dist: sqlalchemy; extra == "utxo"
Requires-Dist: aiosqlite; extra == "utxo"
Requires-Dist: aiomysql; extra == "utxo"
Requires-Dist: greenlet; extra == "utxo"
Requires-Dist: cryptography; extra == "utxo"
Requires-Dist: bitcoinlib==0.7.*; extra == "utxo"
Provides-Extra: evm
Requires-Dist: eth_keys==0.5.*; extra == "evm"
Requires-Dist: eth_utils==4.1.*; extra == "evm"
Requires-Dist: eth_account==0.13.*; extra == "evm"
Dynamic: author
Dynamic: author-email
Dynamic: classifier
Dynamic: description
Dynamic: description-content-type
Dynamic: home-page
Dynamic: keywords
Dynamic: license-file
Dynamic: project-url
Dynamic: provides-extra
Dynamic: requires-dist
Dynamic: summary
